ejpm/__init__.py
ejpm/version.py
ejpm/cli/__init__.py
ejpm/cli/clean.py
ejpm/cli/config.py
ejpm/cli/env.py
ejpm/cli/example_command.py
ejpm/cli/find.py
ejpm/cli/info.py
ejpm/cli/install.py
ejpm/cli/mergedb.py
ejpm/cli/pwd.py
ejpm/cli/req.py
ejpm/cli/rm.py
ejpm/cli/set.py
ejpm/engine/__init__.py
ejpm/engine/api.py
ejpm/engine/commands.py
ejpm/engine/convig.py
ejpm/engine/db.py
ejpm/engine/env_gen.py
ejpm/engine/git_cmake_recipe.py
ejpm/engine/output.py
ejpm/engine/py23.py
ejpm/engine/recipe.py
ejpm/engine/recipe_manager.py
ejpm/engine/standard_actions.py
ejpm/recipes/__init__.py
ejpm/recipes/acts.py
ejpm/recipes/athena_det.py
ejpm/recipes/clhep.py
ejpm/recipes/dd4hep.py
ejpm/recipes/delphes.py
ejpm/recipes/dire.py
ejpm/recipes/easy_profiler.py
ejpm/recipes/eic_smear.py
ejpm/recipes/eigen3.py
ejpm/recipes/ejana.py
ejpm/recipes/fastjet.py
ejpm/recipes/g4e.py
ejpm/recipes/geant.py
ejpm/recipes/genfit.py
ejpm/recipes/hepmc.py
ejpm/recipes/hepmc3.py
ejpm/recipes/jana.py
ejpm/recipes/lhapdf6.py
ejpm/recipes/npdet.py
ejpm/recipes/podio.py
ejpm/recipes/pythia8.py
ejpm/recipes/rave.py
ejpm/recipes/root.py
ejpm/recipes/vgm.py
ejpm-0.3.53.dist-info/LICENSE
ejpm-0.3.53.dist-info/METADATA
ejpm-0.3.53.dist-info/WHEEL
ejpm-0.3.53.dist-info/entry_points.txt
ejpm-0.3.53.dist-info/top_level.txt
ejpm-0.3.53.dist-info/RECORD
