Metadata-Version: 2.1
Name: ejpm
Version: 0.3.53
Summary: EIC Jana Package Manager
Home-page: https://gitlab.com/eic/escalate/ejpm
Author: Dmitry Romanov
Author-email: romanov@jlab.org
License: MIT
Platform: UNKNOWN
Classifier: Development Status :: 4 - Beta
Classifier: License :: OSI Approved :: MIT License
Classifier: Programming Language :: Python :: 2
Classifier: Programming Language :: Python :: 2.7
Classifier: Programming Language :: Python :: 3
Classifier: Programming Language :: Python :: 3.6
Requires-Dist: click
Requires-Dist: appdirs
